definite_sdk/__init__.py
definite_sdk/client.py
definite_sdk/dlt.py
definite_sdk/integration.py
definite_sdk/message.py
definite_sdk/py.typed
definite_sdk/secret.py
definite_sdk/sql.py
definite_sdk/store.py
definite_sdk-0.1.17.dist-info/METADATA
definite_sdk-0.1.17.dist-info/WHEEL
definite_sdk-0.1.17.dist-info/licenses/LICENSE
definite_sdk-0.1.17.dist-info/RECORD
