Metadata-Version: 2.4
Name: definite-sdk
Version: 0.1.17
Summary: Definite SDK for Python
License: MIT
License-File: LICENSE
Author: Definite
Author-email: hello@definite.app
Requires-Python: >=3.9,<4.0
Classifier: License :: OSI Approved :: MIT License
Classifier: Programming Language :: Python :: 3
Classifier: Programming Language :: Python :: 3.9
Classifier: Programming Language :: Python :: 3.10
Classifier: Programming Language :: Python :: 3.11
Classifier: Programming Language :: Python :: 3.12
Classifier: Programming Language :: Python :: 3.13
Classifier: Programming Language :: Python :: 3.14
Provides-Extra: dlt
Requires-Dist: dlt (>=1.0,<2.0) ; extra == "dlt"
Requires-Dist: duckdb (>=1.0,<2.0) ; extra == "dlt"
Requires-Dist: requests (>=2.31.0,<3.0.0)
